setup.py
django_goto_url.egg-info/PKG-INFO
django_goto_url.egg-info/SOURCES.txt
django_goto_url.egg-info/dependency_links.txt
django_goto_url.egg-info/not-zip-safe
django_goto_url.egg-info/requires.txt
django_goto_url.egg-info/top_level.txt
goto_url/__init__.py
goto_url/tests.py
goto_url/urls.py
goto_url/utils.py
goto_url/views.py
goto_url/templatetags/__init__.py
goto_url/templatetags/goto_url.py