Metadata-Version: 1.1
Name: django-goto-url
Version: 0.3
Summary: Wraps external links in base64 and relocate on the special View, later redirect to source URL
Home-page: http://github.com/adw0rd/django-goto-url
Author: Mikhail Andreev
Author-email: x11org@gmail.com
License: BSD
Keywords: django,goto,url,redirect,relocation
Platform: UNKNOWN
Classifier: Environment :: Web Environment
Classifier: Programming Language :: Python
Classifier: Framework :: Django
Classifier: License :: OSI Approved :: BSD License
Classifier: Topic :: Software Development :: Libraries :: Application Frameworks
Classifier: Topic :: Software Development :: Libraries :: Python Modules
